{"is_source_file": false, "format": "", "description": "", "external_files": [], "external_methods": [], "published": [], "classes": [], "methods": [], "calls": [], "search-terms": ["CSS", "variables", "theme", "App", "dark", "light"], "state": 2, "file_id": 12, "knowledge_revision": 18, "git_revision": "9cd55b368849dbd1aab4300680d3572adeea316d", "hash": "22f9e17cc1848b56dbb244518ac2707e", "format-version": 4, "code-base-name": "react_frontend", "filename": "react_frontend/src/App.css", "revision_history": [{"18": "9cd55b368849dbd1aab4300680d3572adeea316d"}]}